{
  "queries": {
    "taoyz9c43e": [
      {
        "mode": "SQL",
        "id": "3Q4kr608dXia",
        "runOn": 1486976224802,
        "runIn": 78,
        "runBy": "grabenertr",
        "connection": "datalabmaster",
        "state": "DONE",
        "futureId": "EgPpxwkW8w3HtG40",
        "hash": "1f83607ba9f796a9965d9c51fdc5ed0c",
        "querySettings": {
          "addLimitToStatement": true,
          "statementsOutOfTransaction": false,
          "extraConf": [],
          "addDkuUdf": false
        },
        "sql": "select * from \"caracteristiques_gecodoed_ban_bano\" where bano_score \u003e ban_score limit 10",
        "expandedSql": "select * from \"caracteristiques_gecodoed_ban_bano\" where bano_score \u003e ban_score limit 10"
      },
      {
        "mode": "SQL",
        "id": "JNVfdtfao7WA",
        "runOn": 1486976265853,
        "runIn": 73,
        "runBy": "grabenertr",
        "connection": "datalabmaster",
        "state": "DONE",
        "futureId": "4QxurZcdhIMmU3J4",
        "hash": "35b4df83ec7fb8a96db76f1c4fbcfbc2",
        "querySettings": {
          "addLimitToStatement": true,
          "statementsOutOfTransaction": false,
          "extraConf": [],
          "addDkuUdf": false
        },
        "sql": "select * from \"caracteristiques_gecodoed_ban_bano\" where ban_city is null and bano_score \u003e 0.5 limit 10",
        "expandedSql": "select * from \"caracteristiques_gecodoed_ban_bano\" where ban_city is null and bano_score \u003e 0.5 limit 10"
      },
      {
        "mode": "SQL",
        "id": "9p9NAumRVmP2",
        "runOn": 1486976367584,
        "runIn": 249,
        "runBy": "grabenertr",
        "connection": "datalabmaster",
        "state": "FAILED",
        "futureId": "Q6AR8OwluexGYqKS",
        "hash": "d91c18597838ba1318792e43993ef8df",
        "querySettings": {
          "addLimitToStatement": true,
          "statementsOutOfTransaction": false,
          "extraConf": [],
          "addDkuUdf": false
        },
        "sql": "select * from \"caracteristiques_gecodoed_ban_bano\" where ban_city is null and bano_score \u003e 0.5 limit 10\nand substring(bano_citycode, 0,2) \u003d\u003d dep",
        "expandedSql": "select * from \"caracteristiques_gecodoed_ban_bano\" where ban_city is null and bano_score \u003e 0.5 limit 10\nand substring(bano_citycode, 0,2) \u003d\u003d dep"
      },
      {
        "mode": "SQL",
        "id": "zK8IXch5mGY0",
        "runOn": 1486976373515,
        "runIn": 40,
        "runBy": "grabenertr",
        "connection": "datalabmaster",
        "state": "FAILED",
        "futureId": "xgWr9iMUTv1f1yqe",
        "hash": "ac15a729f200fde90a40a0ba177bdf89",
        "querySettings": {
          "addLimitToStatement": true,
          "statementsOutOfTransaction": false,
          "extraConf": [],
          "addDkuUdf": false
        },
        "sql": "select * from \"caracteristiques_gecodoed_ban_bano\" where ban_city is null and bano_score \u003e 0.5 limit 10\nand substring(bano_citycode, 0,2) \u003d dep",
        "expandedSql": "select * from \"caracteristiques_gecodoed_ban_bano\" where ban_city is null and bano_score \u003e 0.5 limit 10\nand substring(bano_citycode, 0,2) \u003d dep"
      },
      {
        "mode": "SQL",
        "id": "ijxNRjXBBDuY",
        "runOn": 1486976383376,
        "runIn": 65,
        "runBy": "grabenertr",
        "connection": "datalabmaster",
        "state": "DONE",
        "futureId": "UYeFLpuD39o1VKjM",
        "hash": "9ead4535fdc26f181597a906557ae731",
        "querySettings": {
          "addLimitToStatement": true,
          "statementsOutOfTransaction": false,
          "extraConf": [],
          "addDkuUdf": false
        },
        "sql": "select * from \"caracteristiques_gecodoed_ban_bano\" where ban_city is null and bano_score \u003e 0.5 \nand substring(bano_citycode, 0,2) \u003d dep\nlimit 10",
        "expandedSql": "select * from \"caracteristiques_gecodoed_ban_bano\" where ban_city is null and bano_score \u003e 0.5 \nand substring(bano_citycode, 0,2) \u003d dep\nlimit 10"
      },
      {
        "mode": "SQL",
        "id": "EA8V4MVEgMVt",
        "runOn": 1486976398425,
        "runIn": 47,
        "runBy": "grabenertr",
        "connection": "datalabmaster",
        "state": "FAILED",
        "futureId": "0jFnHIVSjZ6tmZsa",
        "hash": "8639eb822b4b34397409b3673a2fea3b",
        "querySettings": {
          "addLimitToStatement": true,
          "statementsOutOfTransaction": false,
          "extraConf": [],
          "addDkuUdf": false
        },
        "sql": "select * from \"caracteristiques_gecodoed_ban_bano\" where ban_city is null and bano_score \u003e 0.5 \nand substring(bano_citycode, 0,2) \u003d dep\nlimit 10\n\nselect substring(\"12345\", 0, 2)",
        "expandedSql": "select * from \"caracteristiques_gecodoed_ban_bano\" where ban_city is null and bano_score \u003e 0.5 \nand substring(bano_citycode, 0,2) \u003d dep\nlimit 10\n\nselect substring(\"12345\", 0, 2)"
      },
      {
        "mode": "SQL",
        "id": "lVcmmggPtup6",
        "runOn": 1486976400634,
        "runIn": 65,
        "runBy": "grabenertr",
        "connection": "datalabmaster",
        "state": "FAILED",
        "futureId": "a5DcuXyhqqUMkOdI",
        "hash": "2aa1dcc755e3598a0f2082f2bfad24da",
        "querySettings": {
          "addLimitToStatement": true,
          "statementsOutOfTransaction": false,
          "extraConf": [],
          "addDkuUdf": false
        },
        "sql": "select * from \"caracteristiques_gecodoed_ban_bano\" where ban_city is null and bano_score \u003e 0.5 \nand substring(bano_citycode, 0,2) \u003d dep\nlimit 10;\n\nselect substring(\"12345\", 0, 2)",
        "expandedSql": "select * from \"caracteristiques_gecodoed_ban_bano\" where ban_city is null and bano_score \u003e 0.5 \nand substring(bano_citycode, 0,2) \u003d dep\nlimit 10;\n\nselect substring(\"12345\", 0, 2)"
      },
      {
        "mode": "SQL",
        "id": "UmP3JHzbYVC2",
        "runOn": 1486976406303,
        "runIn": 66,
        "runBy": "grabenertr",
        "connection": "datalabmaster",
        "state": "DONE",
        "futureId": "SlveMcm533jVbDpz",
        "hash": "af640ad26dff5cb772b8c191ee84e2c9",
        "querySettings": {
          "addLimitToStatement": true,
          "statementsOutOfTransaction": false,
          "extraConf": [],
          "addDkuUdf": false
        },
        "sql": "select * from \"caracteristiques_gecodoed_ban_bano\" where ban_city is null and bano_score \u003e 0.5 \nand substring(bano_citycode, 0,2) \u003d dep\nlimit 10;\n\nselect substring(\u002712345\u0027, 0, 2)",
        "expandedSql": "select * from \"caracteristiques_gecodoed_ban_bano\" where ban_city is null and bano_score \u003e 0.5 \nand substring(bano_citycode, 0,2) \u003d dep\nlimit 10;\n\nselect substring(\u002712345\u0027, 0, 2)"
      },
      {
        "mode": "SQL",
        "id": "SrAyzlyh9Cdx",
        "runOn": 1486976411256,
        "runIn": 80,
        "runBy": "grabenertr",
        "connection": "datalabmaster",
        "state": "DONE",
        "futureId": "HXesYD0D3cqg0s3p",
        "hash": "30fecf4a9d3518f50303076911b07247",
        "querySettings": {
          "addLimitToStatement": true,
          "statementsOutOfTransaction": false,
          "extraConf": [],
          "addDkuUdf": false
        },
        "sql": "select * from \"caracteristiques_gecodoed_ban_bano\" where ban_city is null and bano_score \u003e 0.5 \nand substring(bano_citycode, 0,2) \u003d dep\nlimit 10;\n\nselect substring(\u002712345\u0027, 0, 3)",
        "expandedSql": "select * from \"caracteristiques_gecodoed_ban_bano\" where ban_city is null and bano_score \u003e 0.5 \nand substring(bano_citycode, 0,2) \u003d dep\nlimit 10;\n\nselect substring(\u002712345\u0027, 0, 3)"
      },
      {
        "mode": "SQL",
        "id": "M71ST6fC32UM",
        "runOn": 1486976418671,
        "runIn": 62,
        "runBy": "grabenertr",
        "connection": "datalabmaster",
        "state": "DONE",
        "futureId": "tUinMhJSxtV7FU1H",
        "hash": "0b8f5ff96600e25c1ee3faf34a2355e0",
        "querySettings": {
          "addLimitToStatement": true,
          "statementsOutOfTransaction": false,
          "extraConf": [],
          "addDkuUdf": false
        },
        "sql": "select * from \"caracteristiques_gecodoed_ban_bano\" where ban_city is null and bano_score \u003e 0.5 \nand substring(bano_citycode, 0, 3) \u003d dep\nlimit 10;\n\n",
        "expandedSql": "select * from \"caracteristiques_gecodoed_ban_bano\" where ban_city is null and bano_score \u003e 0.5 \nand substring(bano_citycode, 0, 3) \u003d dep\nlimit 10;\n\n"
      },
      {
        "mode": "SQL",
        "id": "ITyOJynzoNOU",
        "runOn": 1486976427177,
        "runIn": 62,
        "runBy": "grabenertr",
        "connection": "datalabmaster",
        "state": "DONE",
        "futureId": "gR3GATdQAuGhLqvR",
        "hash": "3ac20ede9302947c504158fb6d75d6ed",
        "querySettings": {
          "addLimitToStatement": true,
          "statementsOutOfTransaction": false,
          "extraConf": [],
          "addDkuUdf": false
        },
        "sql": "select * from \"caracteristiques_gecodoed_ban_bano\" where ban_city is null and bano_score \u003e 0.5 \n\nlimit 10;\n\n",
        "expandedSql": "select * from \"caracteristiques_gecodoed_ban_bano\" where ban_city is null and bano_score \u003e 0.5 \n\nlimit 10;\n\n"
      },
      {
        "mode": "SQL",
        "id": "Uszw69c26e02",
        "runOn": 1486976435340,
        "runIn": 135,
        "runBy": "grabenertr",
        "connection": "datalabmaster",
        "state": "DONE",
        "futureId": "c0tNRSQ034Rej10M",
        "hash": "a75e99ae9465d69ebd9f50e326da4f33",
        "querySettings": {
          "addLimitToStatement": true,
          "statementsOutOfTransaction": false,
          "extraConf": [],
          "addDkuUdf": false
        },
        "sql": "select count(1) from \"caracteristiques_gecodoed_ban_bano\" where ban_city is null and bano_score \u003e 0.5 \n\nlimit 10;\n\n",
        "expandedSql": "select count(1) from \"caracteristiques_gecodoed_ban_bano\" where ban_city is null and bano_score \u003e 0.5 \n\nlimit 10;\n\n"
      },
      {
        "mode": "SQL",
        "id": "sNUHbVS8sC1S",
        "runOn": 1486976463822,
        "runIn": 88,
        "runBy": "grabenertr",
        "connection": "datalabmaster",
        "state": "DONE",
        "futureId": "WhSfdwnjPJDzQTPs",
        "hash": "f6d76bacdb403845319b03af9bd898b2",
        "querySettings": {
          "addLimitToStatement": true,
          "statementsOutOfTransaction": false,
          "extraConf": [],
          "addDkuUdf": false
        },
        "sql": "select *, substring(bano_citycode, 0, 3) from \"caracteristiques_gecodoed_ban_bano\" where ban_city is null and bano_score \u003e 0.5 \n\nlimit 10;\n\n",
        "expandedSql": "select *, substring(bano_citycode, 0, 3) from \"caracteristiques_gecodoed_ban_bano\" where ban_city is null and bano_score \u003e 0.5 \n\nlimit 10;\n\n"
      },
      {
        "mode": "SQL",
        "id": "IZHfRlmHIReo",
        "runOn": 1486976476030,
        "runIn": 70,
        "runBy": "grabenertr",
        "connection": "datalabmaster",
        "state": "DONE",
        "futureId": "OiW7m42Xogms6y6A",
        "hash": "71c263d4f74ace853afc81ee921b10ec",
        "querySettings": {
          "addLimitToStatement": true,
          "statementsOutOfTransaction": false,
          "extraConf": [],
          "addDkuUdf": false
        },
        "sql": "select *, substring(bano_postcode, 0, 3) from \"caracteristiques_gecodoed_ban_bano\" where ban_city is null and bano_score \u003e 0.5 \n\nlimit 10;\n\n",
        "expandedSql": "select *, substring(bano_postcode, 0, 3) from \"caracteristiques_gecodoed_ban_bano\" where ban_city is null and bano_score \u003e 0.5 \n\nlimit 10;\n\n"
      },
      {
        "mode": "SQL",
        "id": "yGudyjbAYTqh",
        "runOn": 1486976489830,
        "runIn": 64,
        "runBy": "grabenertr",
        "connection": "datalabmaster",
        "state": "DONE",
        "futureId": "326ApB1zKkZgErir",
        "hash": "949bff1084acf7e3cfd00a93ffc5c95c",
        "querySettings": {
          "addLimitToStatement": true,
          "statementsOutOfTransaction": false,
          "extraConf": [],
          "addDkuUdf": false
        },
        "sql": "select * from \"caracteristiques_gecodoed_ban_bano\" where ban_city is null and bano_score \u003e 0.5 \nand dep \u003d substring(bano_postcode, 0, 3)\nlimit 10;\n\n",
        "expandedSql": "select * from \"caracteristiques_gecodoed_ban_bano\" where ban_city is null and bano_score \u003e 0.5 \nand dep \u003d substring(bano_postcode, 0, 3)\nlimit 10;\n\n"
      },
      {
        "mode": "SQL",
        "id": "91MhNCI6RDTU",
        "runOn": 1486976495824,
        "runIn": 156,
        "runBy": "grabenertr",
        "connection": "datalabmaster",
        "state": "DONE",
        "futureId": "63q2tUdEFQVAfYGC",
        "hash": "807e1e6058c4c476785b97d0a9f7ee55",
        "querySettings": {
          "addLimitToStatement": true,
          "statementsOutOfTransaction": false,
          "extraConf": [],
          "addDkuUdf": false
        },
        "sql": "select count(*) from \"caracteristiques_gecodoed_ban_bano\" where ban_city is null and bano_score \u003e 0.5 \nand dep \u003d substring(bano_postcode, 0, 3)\nlimit 10;\n\n",
        "expandedSql": "select count(*) from \"caracteristiques_gecodoed_ban_bano\" where ban_city is null and bano_score \u003e 0.5 \nand dep \u003d substring(bano_postcode, 0, 3)\nlimit 10;\n\n"
      },
      {
        "mode": "SQL",
        "id": "zU3RcFkNmVxU",
        "runOn": 1486976766133,
        "runIn": 66,
        "runBy": "grabenertr",
        "connection": "datalabmaster",
        "state": "DONE",
        "futureId": "P2lRmbSPle2Xx34D",
        "hash": "26dbb07ae75b579564eaa2d2795e4793",
        "querySettings": {
          "addLimitToStatement": true,
          "statementsOutOfTransaction": false,
          "extraConf": [],
          "addDkuUdf": false
        },
        "sql": "select * from \"caracteristiques_gecodoed_ban_bano\" where ban_city is null and bano_score \u003e 0.5 \nand dep \u003d substring(bano_postcode, 0, 3)\nlimit 100;\n\n",
        "expandedSql": "select * from \"caracteristiques_gecodoed_ban_bano\" where ban_city is null and bano_score \u003e 0.5 \nand dep \u003d substring(bano_postcode, 0, 3)\nlimit 100;\n\n"
      }
    ]
  }
}